{
  "$type": "slotData",
  "depth": 0,
  "data": {
    "parent": {
      "targetId": "Root",
      "targetType": "[FrooxEngine]FrooxEngine.Slot",
      "id": "Reso_75E0"
    },
    "position": {
      "value": {
        "x": 0,
        "y": 1,
        "z": 0
      },
      "id": "Reso_75E1"
    },
    "rotation": {
      "value": {
        "x": 0,
        "y": 0,
        "z": 0,
        "w": 1
      },
      "id": "Reso_75E2"
    },
    "scale": {
      "value": {
        "x": 0.1,
        "y": 0.1,
        "z": 0.1
      },
      "id": "Reso_75E3"
    },
    "isActive": {
      "value": true,
      "id": "Reso_75E4"
    },
    "isPersistent": {
      "value": false,
      "id": "Reso_75E5"
    },
    "name": {
      "value": "DataCollectionTest",
      "id": "Reso_75E6"
    },
    "tag": {
      "value": "",
      "id": "Reso_75E7"
    },
    "orderOffset": {
      "value": 0,
      "id": "Reso_75E8"
    },
    "components": [],
    "children": null,
    "id": "test_collect_1771415011141",
    "isReferenceOnly": false
  },
  "sourceMessageId": "tsrl_j9d7co6flo_m",
  "success": true,
  "errorInfo": null
}
