{
  "componentType": "[FrooxEngine]FrooxEngine.Grabbable",
  "addResponse": {
    "$type": "newEntityId",
    "entityId": "test_[FrooxEngine]FrooxEngine_Grabbable_1770909221652",
    "sourceMessageId": "6162106c-6d57-42b5-9faa-ad7cf648c321",
    "success": true,
    "errorInfo": null
  },
  "getResponse": {
    "$type": "componentData",
    "data": {
      "componentType": "[FrooxEngine]FrooxEngine.Grabbable",
      "members": {
        "persistent": {
          "$type": "bool",
          "value": true,
          "id": "Reso_12951"
        },
        "UpdateOrder": {
          "$type": "int",
          "value": 0,
          "id": "Reso_12952"
        },
        "Enabled": {
          "$type": "bool",
          "value": true,
          "id": "Reso_12953"
        },
        "ReparentOnRelease": {
          "$type": "bool",
          "value": true,
          "id": "Reso_12954"
        },
        "PreserveUserSpace": {
          "$type": "bool",
          "value": true,
          "id": "Reso_12955"
        },
        "DestroyOnRelease": {
          "$type": "bool",
          "value": false,
          "id": "Reso_12956"
        },
        "GrabPriority": {
          "$type": "int",
          "value": 0,
          "id": "Reso_12957"
        },
        "GrabPriorityWhenGrabbed": {
          "$type": "int?",
          "value": null,
          "id": "Reso_12958"
        },
        "CustomCanGrabCheck": {
          "$type": "reference",
          "targetId": null,
          "targetType": "[FrooxEngine]FrooxEngine.GrabCheck",
          "id": "Reso_12959"
        },
        "EditModeOnly": {
          "$type": "bool",
          "value": false,
          "id": "Reso_1295A"
        },
        "AllowSteal": {
          "$type": "bool",
          "value": false,
          "id": "Reso_1295B"
        },
        "DropOnDisable": {
          "$type": "bool",
          "value": true,
          "id": "Reso_1295C"
        },
        "ActiveUserFilter": {
          "$type": "enum",
          "value": "Disabled",
          "enumType": "ActiveUserHandling",
          "id": "Reso_1295D"
        },
        "OnlyUsers": {
          "$type": "list",
          "elements": [],
          "id": "Reso_1295E"
        },
        "Scalable": {
          "$type": "bool",
          "value": false,
          "id": "Reso_1295F"
        },
        "Receivable": {
          "$type": "bool",
          "value": true,
          "id": "Reso_12960"
        },
        "AllowOnlyPhysicalGrab": {
          "$type": "bool",
          "value": false,
          "id": "Reso_12961"
        },
        "_grabber": {
          "$type": "reference",
          "targetId": null,
          "targetType": "[FrooxEngine]FrooxEngine.Grabber",
          "id": "Reso_12962"
        },
        "_lastParent": {
          "$type": "reference",
          "targetId": null,
          "targetType": "[FrooxEngine]FrooxEngine.Slot",
          "id": "Reso_12963"
        },
        "_lastParentIsUserSpace": {
          "$type": "bool",
          "value": false,
          "id": "Reso_12964"
        },
        "__legacyActiveUserRootOnly": {
          "$type": "bool",
          "value": false,
          "id": "Reso_12965"
        }
      },
      "id": "test_[FrooxEngine]FrooxEngine_Grabbable_1770909221652",
      "isReferenceOnly": false
    },
    "sourceMessageId": "40eb47e2-d2fb-4dc1-855e-d8709d598964",
    "success": true,
    "errorInfo": null
  }
}
