{
  "componentType": "[FrooxEngine]FrooxEngine.MeshRenderer",
  "addResponse": {
    "$type": "response",
    "sourceMessageId": "790ded60-c8fd-4ae5-b1f2-7c2226f01156",
    "success": true,
    "errorInfo": null
  },
  "getResponse": {
    "$type": "componentData",
    "data": {
      "componentType": "[FrooxEngine]FrooxEngine.MeshRenderer",
      "members": {
        "persistent": {
          "$type": "bool",
          "value": true,
          "id": "Reso_2FE"
        },
        "UpdateOrder": {
          "$type": "int",
          "value": 0,
          "id": "Reso_2FF"
        },
        "Enabled": {
          "$type": "bool",
          "value": true,
          "id": "Reso_300"
        },
        "Mesh": {
          "$type": "reference",
          "targetId": null,
          "targetType": "[FrooxEngine]FrooxEngine.IAssetProvider<[FrooxEngine]FrooxEngine.Mesh>",
          "id": "Reso_301"
        },
        "Materials": {
          "$type": "list",
          "elements": [],
          "id": "Reso_302"
        },
        "MaterialPropertyBlocks": {
          "$type": "list",
          "elements": [],
          "id": "Reso_303"
        },
        "ShadowCastMode": {
          "$type": "enum",
          "value": "On",
          "enumType": "ShadowCastMode",
          "id": "Reso_304"
        },
        "MotionVectorMode": {
          "$type": "enum",
          "value": "Object",
          "enumType": "MotionVectorMode",
          "id": "Reso_305"
        },
        "SortingOrder": {
          "$type": "int",
          "value": 0,
          "id": "Reso_306"
        }
      },
      "id": "test_[FrooxEngine]FrooxEngine_MeshRenderer_1770376790868",
      "isReferenceOnly": false
    },
    "sourceMessageId": "c04ec42a-ba1f-4059-b9b8-29c360b23f0b",
    "success": true,
    "errorInfo": null
  }
}
